readercli/__init__.py
readercli/__main__.py
readercli/api.py
readercli/commands.py
readercli/constants.py
readercli/data.py
readercli/layout.py
readercli/models.py
readercli/py.typed
readercli/utils.py
readercli/reading_list/__init__.py
readercli/reading_list/extractors.py
readwise_reader_cli-1.0.0.dist-info/entry_points.txt
readwise_reader_cli-1.0.0.dist-info/LICENSE
readwise_reader_cli-1.0.0.dist-info/WHEEL
readwise_reader_cli-1.0.0.dist-info/METADATA
readwise_reader_cli-1.0.0.dist-info/RECORD
