Metadata-Version: 2.1
Name: readwise-reader-cli
Version: 1.0.0
Summary: Engage with your Readwise Reader library through your command-line.
Keywords: api,readwise,cli,python
Author-email: Scott Carvalho <scottcarvalho71@gmail.com>
Requires-Python: >=3.8
Classifier: License :: OSI Approved :: MIT License
Classifier: Programming Language :: Python :: 3
Classifier: Programming Language :: Python :: 3.8
Classifier: Programming Language :: Python :: 3.9
Classifier: Programming Language :: Python :: 3.10
Classifier: Programming Language :: Python :: 3.11
Classifier: Programming Language :: Python :: 3.12
Classifier: Programming Language :: Python :: 3 :: Only
Requires-Dist: click >= 8.1.3
Requires-Dist: python-dateutil
Requires-Dist: requests
Requires-Dist: beautifulsoup4
Requires-Dist: python-dotenv
Requires-Dist: xdg-base-dirs
Requires-Dist: rich
Requires-Dist: pydantic
Requires-Dist: black ; extra == "dev"
Requires-Dist: isort ; extra == "dev"
Requires-Dist: pre-commit ; extra == "test"
Requires-Dist: pytest ; extra == "test"
Project-URL: Homepage, https://github.com/Scarvy/readwise-reader-cli
Provides-Extra: dev
Provides-Extra: test
